{
  "project_info": {
    "project_number": "1083813582426",
    "firebase_url": "https://check-stocks-95c2d.firebaseio.com",
    "project_id": "check-stocks-95c2d",
    "storage_bucket": "check-stocks-95c2d.appspot.com"
  },
  "client": [
    {
      "client_info": {
        "mobilesdk_app_id": "1:1083813582426:android:8e048206ae3f61df8caa63",
        "android_client_info": {
          "package_name": "com.student.checkStocks"
        }
      },
      "oauth_client": [
        {
          "client_id": "1083813582426-28haaf6vd9f825kkpckn681egel05514.apps.googleusercontent.com",
          "client_type": 3
        }
      ],
      "api_key": [
        {
          "current_key": "AIzaSyBS-PnmcrN_3ITdX0aodn7AfRZoTx2FA8M"
        }
      ],
      "services": {
        "appinvite_service": {
          "other_platform_oauth_client": [
            {
              "client_id": "1083813582426-28haaf6vd9f825kkpckn681egel05514.apps.googleusercontent.com",
              "client_type": 3
            }
          ]
        }
      }
    }
  ],
  "configuration_version": "1"
}